[
  {
    "time": "2022-12-31",
    "open": 312,
    "high": 610,
    "low": 298,
    "close": 471,
    "volume": 161594800,
    "ma36": null,
    "dev36": null,
    "tav36": null
  },
  {
    "time": "2023-01-31",
    "open": 520,
    "high": 946,
    "low": 444,
    "close": 920,
    "volume": 211442300,
    "ma36": null,
    "dev36": null,
    "tav36": null
  },
  {
    "time": "2023-02-28",
    "open": 1070,
    "high": 1275,
    "low": 915,
    "close": 1048,
    "volume": 67369700,
    "ma36": null,
    "dev36": null,
    "tav36": null
  },
  {
    "time": "2023-03-31",
    "open": 1063,
    "high": 1385,
    "low": 940,
    "close": 1146,
    "volume": 82308500,
    "ma36": null,
    "dev36": null,
    "tav36": null
  },
  {
    "time": "2023-04-30",
    "open": 1153,
    "high": 1197,
    "low": 941,
    "close": 1101,
    "volume": 34404200,
    "ma36": null,
    "dev36": null,
    "tav36": null
  },
  {
    "time": "2023-05-31",
    "open": 1100,
    "high": 1240,
    "low": 941,
    "close": 963,
    "volume": 21588700,
    "ma36": null,
    "dev36": null,
    "tav36": null
  },
  {
    "time": "2023-06-30",
    "open": 985,
    "high": 988,
    "low": 633,
    "close": 870,
    "volume": 26723500,
    "ma36": null,
    "dev36": null,
    "tav36": null
  },
  {
    "time": "2023-07-31",
    "open": 896,
    "high": 995,
    "low": 653,
    "close": 709,
    "volume": 18828200,
    "ma36": null,
    "dev36": null,
    "tav36": null
  },
  {
    "time": "2023-08-31",
    "open": 718,
    "high": 851,
    "low": 550,
    "close": 575,
    "volume": 10714800,
    "ma36": null,
    "dev36": null,
    "tav36": null
  },
  {
    "time": "2023-09-30",
    "open": 570,
    "high": 637,
    "low": 494,
    "close": 556,
    "volume": 9589500,
    "ma36": null,
    "dev36": null,
    "tav36": null
  },
  {
    "time": "2023-10-31",
    "open": 555,
    "high": 596,
    "low": 429,
    "close": 471,
    "volume": 5504200,
    "ma36": null,
    "dev36": null,
    "tav36": null
  },
  {
    "time": "2023-11-30",
    "open": 474,
    "high": 520,
    "low": 384,
    "close": 388,
    "volume": 4118300,
    "ma36": null,
    "dev36": null,
    "tav36": null
  },
  {
    "time": "2023-12-31",
    "open": 384,
    "high": 393,
    "low": 316,
    "close": 344,
    "volume": 6583700,
    "ma36": null,
    "dev36": null,
    "tav36": null
  },
  {
    "time": "2024-01-31",
    "open": 337,
    "high": 602,
    "low": 328,
    "close": 553,
    "volume": 41438400,
    "ma36": null,
    "dev36": null,
    "tav36": null
  },
  {
    "time": "2024-02-29",
    "open": 548,
    "high": 849,
    "low": 479,
    "close": 763,
    "volume": 44432900,
    "ma36": null,
    "dev36": null,
    "tav36": null
  },
  {
    "time": "2024-03-31",
    "open": 770,
    "high": 1143,
    "low": 664,
    "close": 959,
    "volume": 44252500,
    "ma36": null,
    "dev36": null,
    "tav36": null
  },
  {
    "time": "2024-04-30",
    "open": 974,
    "high": 1061,
    "low": 702,
    "close": 786,
    "volume": 32429400,
    "ma36": null,
    "dev36": null,
    "tav36": null
  },
  {
    "time": "2024-05-31",
    "open": 780,
    "high": 918,
    "low": 740,
    "close": 883,
    "volume": 9651700,
    "ma36": null,
    "dev36": null,
    "tav36": null
  },
  {
    "time": "2024-06-30",
    "open": 918,
    "high": 1627,
    "low": 905,
    "close": 1516,
    "volume": 50443400,
    "ma36": null,
    "dev36": null,
    "tav36": null
  },
  {
    "time": "2024-07-31",
    "open": 1645,
    "high": 2313,
    "low": 1015,
    "close": 1065,
    "volume": 77774100,
    "ma36": null,
    "dev36": null,
    "tav36": null
  },
  {
    "time": "2024-08-31",
    "open": 1043,
    "high": 1051,
    "low": 708,
    "close": 804,
    "volume": 31056100,
    "ma36": null,
    "dev36": null,
    "tav36": null
  },
  {
    "time": "2024-09-30",
    "open": 811,
    "high": 825,
    "low": 641,
    "close": 684,
    "volume": 10273900,
    "ma36": null,
    "dev36": null,
    "tav36": null
  },
  {
    "time": "2024-10-31",
    "open": 683,
    "high": 727,
    "low": 499,
    "close": 521,
    "volume": 17466500,
    "ma36": null,
    "dev36": null,
    "tav36": null
  },
  {
    "time": "2024-11-30",
    "open": 506,
    "high": 546,
    "low": 478,
    "close": 543,
    "volume": 6844100,
    "ma36": null,
    "dev36": null,
    "tav36": null
  },
  {
    "time": "2024-12-31",
    "open": 573,
    "high": 578,
    "low": 401,
    "close": 461,
    "volume": 11924600,
    "ma36": null,
    "dev36": null,
    "tav36": null
  },
  {
    "time": "2025-01-31",
    "open": 485,
    "high": 833,
    "low": 466,
    "close": 789,
    "volume": 46363700,
    "ma36": null,
    "dev36": null,
    "tav36": null
  },
  {
    "time": "2025-02-28",
    "open": 785,
    "high": 1038,
    "low": 738,
    "close": 764,
    "volume": 57650300,
    "ma36": null,
    "dev36": null,
    "tav36": null
  },
  {
    "time": "2025-03-31",
    "open": 900,
    "high": 1118,
    "low": 805,
    "close": 873,
    "volume": 58852300,
    "ma36": null,
    "dev36": null,
    "tav36": null
  },
  {
    "time": "2025-04-30",
    "open": 875,
    "high": 876,
    "low": 641,
    "close": 844,
    "volume": 24769200,
    "ma36": null,
    "dev36": null,
    "tav36": null
  },
  {
    "time": "2025-05-31",
    "open": 840,
    "high": 1199,
    "low": 794,
    "close": 1133,
    "volume": 44587400,
    "ma36": null,
    "dev36": null,
    "tav36": null
  },
  {
    "time": "2025-06-30",
    "open": 1180,
    "high": 1471,
    "low": 991,
    "close": 1028,
    "volume": 101985800,
    "ma36": null,
    "dev36": null,
    "tav36": null
  },
  {
    "time": "2025-07-31",
    "open": 1049,
    "high": 1245,
    "low": 896,
    "close": 1029,
    "volume": 79989500,
    "ma36": null,
    "dev36": null,
    "tav36": null
  },
  {
    "time": "2025-08-31",
    "open": 1010,
    "high": 1237,
    "low": 999,
    "close": 1133,
    "volume": 34820200,
    "ma36": null,
    "dev36": null,
    "tav36": null
  },
  {
    "time": "2025-09-30",
    "open": 1150,
    "high": 1255,
    "low": 997,
    "close": 1010,
    "volume": 20766800,
    "ma36": null,
    "dev36": null,
    "tav36": null
  },
  {
    "time": "2025-10-31",
    "open": 931,
    "high": 1016,
    "low": 647,
    "close": 684,
    "volume": 26999400,
    "ma36": null,
    "dev36": null,
    "tav36": null
  },
  {
    "time": "2025-11-30",
    "open": 683,
    "high": 714,
    "low": 551,
    "close": 566,
    "volume": 8213700,
    "ma36": 804.3,
    "dev36": -29.6,
    "tav36": 37938377522.2
  },
  {
    "time": "2025-12-31",
    "open": 562,
    "high": 614,
    "low": 498,
    "close": 599,
    "volume": 11353800,
    "ma36": 807.8,
    "dev36": -25.8,
    "tav36": 36013093505.6
  },
  {
    "time": "2026-01-31",
    "open": 609,
    "high": 790,
    "low": 591,
    "close": 777,
    "volume": 20891000,
    "ma36": 803.8,
    "dev36": -3.3,
    "tav36": 31060465477.8
  },
  {
    "time": "2026-02-28",
    "open": 762,
    "high": 858,
    "low": 581,
    "close": 656,
    "volume": 38333600,
    "ma36": 792.9,
    "dev36": -17.3,
    "tav36": 29797782033.3
  },
  {
    "time": "2026-03-31",
    "open": 650,
    "high": 680,
    "low": 601,
    "close": 651,
    "volume": 7053800,
    "ma36": 779.2,
    "dev36": -16.5,
    "tav36": 27305184333.3
  }
]